points/__init__.py
points/checks.py
points/geometry.py
points/matrices.py
points/vectors.py
points-0.3.0.dist-info/DESCRIPTION.rst
points-0.3.0.dist-info/METADATA
points-0.3.0.dist-info/RECORD
points-0.3.0.dist-info/WHEEL
points-0.3.0.dist-info/metadata.json
points-0.3.0.dist-info/top_level.txt
