Metadata-Version: 2.0
Name: points
Version: 0.3.0
Summary: A pure-Python geometry and linear algebra library
Home-page: https://points.samireland.com
Author: Sam Ireland
Author-email: mail@samireland.com
License: MIT
Keywords: geometry trigonometry vectors matrices linear-algebra
Platform: UNKNOWN
Classifier: Development Status :: 4 - Beta
Classifier: Intended Audience :: Science/Research
Classifier: License :: OSI Approved :: MIT License
Classifier: Topic :: Scientific/Engineering :: Mathematics
Classifier: Programming Language :: Python :: 3
Classifier: Programming Language :: Python :: 3.5
Classifier: Programming Language :: Python :: 3.6
